odoo/addons/pos_loyalty_redeem_payment/README.rst
odoo/addons/pos_loyalty_redeem_payment/__init__.py
odoo/addons/pos_loyalty_redeem_payment/__manifest__.py
odoo/addons/pos_loyalty_redeem_payment/i18n/es.po
odoo/addons/pos_loyalty_redeem_payment/i18n/fr.po
odoo/addons/pos_loyalty_redeem_payment/i18n/it.po
odoo/addons/pos_loyalty_redeem_payment/i18n/pos_loyalty_redeem_payment.pot
odoo/addons/pos_loyalty_redeem_payment/models/__init__.py
odoo/addons/pos_loyalty_redeem_payment/models/loyalty_program.py
odoo/addons/pos_loyalty_redeem_payment/models/pos_config.py
odoo/addons/pos_loyalty_redeem_payment/models/pos_order.py
odoo/addons/pos_loyalty_redeem_payment/models/pos_payment.py
odoo/addons/pos_loyalty_redeem_payment/models/pos_payment_method.py
odoo/addons/pos_loyalty_redeem_payment/models/pos_session.py
odoo/addons/pos_loyalty_redeem_payment/readme/CONFIGURE.rst
odoo/addons/pos_loyalty_redeem_payment/readme/CONTRIBUTORS.rst
odoo/addons/pos_loyalty_redeem_payment/readme/DESCRIPTION.rst
odoo/addons/pos_loyalty_redeem_payment/readme/ROADMAP.rst
odoo/addons/pos_loyalty_redeem_payment/readme/USAGE.rst
odoo/addons/pos_loyalty_redeem_payment/static/description/icon.png
odoo/addons/pos_loyalty_redeem_payment/static/description/index.html
odoo/addons/pos_loyalty_redeem_payment/static/img/paymentMethod.png
odoo/addons/pos_loyalty_redeem_payment/static/img/paymentMethodCheck.png
odoo/addons/pos_loyalty_redeem_payment/static/img/redeemMethod.png
odoo/addons/pos_loyalty_redeem_payment/static/img/usage_1_code_popup.png
odoo/addons/pos_loyalty_redeem_payment/static/img/usage_2_amount_popup.png
odoo/addons/pos_loyalty_redeem_payment/static/img/usage_3_payment_line.png
odoo/addons/pos_loyalty_redeem_payment/static/src/js/PaymentScreen.esm.js
odoo/addons/pos_loyalty_redeem_payment/static/src/js/ResponsiveNumberPopup.esm.js
odoo/addons/pos_loyalty_redeem_payment/static/src/js/models.esm.js
odoo/addons/pos_loyalty_redeem_payment/static/src/scss/responsive_number_popup.scss
odoo_addon_pos_loyalty_redeem_payment-16.0.1.0.2.dist-info/METADATA
odoo_addon_pos_loyalty_redeem_payment-16.0.1.0.2.dist-info/WHEEL
odoo_addon_pos_loyalty_redeem_payment-16.0.1.0.2.dist-info/top_level.txt
odoo_addon_pos_loyalty_redeem_payment-16.0.1.0.2.dist-info/RECORD
