Metadata-Version: 2.1
Name: odoo-addon-pos-loyalty-redeem-payment
Version: 16.0.1.0.2
Summary: Use vouchers as payment method in pos orders
Home-page: https://github.com/OCA/pos
Author: Odoo Community Association (OCA), FactorLibre
Author-email: support@odoo-community.org
License: LGPL-3
Platform: UNKNOWN
Classifier: Programming Language :: Python
Classifier: Framework :: Odoo
Classifier: Framework :: Odoo :: 16.0
Classifier: License :: OSI Approved :: GNU Lesser General Public License v3 (LGPLv3)
Requires-Python: >=3.10
Requires-Dist: odoo <16.1dev,>=16.0a
